logyca_postgres/__init__.py
logyca_postgres/dependencies/__init__.py
logyca_postgres/dependencies/conn_postgres_async.py
logyca_postgres/dependencies/conn_postgres_sync.py
logyca_postgres/utils/__init__.py
logyca_postgres/utils/helpers/__init__.py
logyca_postgres/utils/helpers/functions.py
logyca_postgres/utils/helpers/singleton.py
logyca_postgres-0.1.7.dist-info/METADATA
logyca_postgres-0.1.7.dist-info/WHEEL
logyca_postgres-0.1.7.dist-info/RECORD
